dispomail/Dispomail.py
dispomail/__init__.py
dispomail/dispomail.py
dispomail-0.1.0.dist-info/LICENSE
dispomail-0.1.0.dist-info/METADATA
dispomail-0.1.0.dist-info/WHEEL
dispomail-0.1.0.dist-info/top_level.txt
dispomail-0.1.0.dist-info/RECORD
